{
  "kind": "youtube#videoListResponse",
  "etag": "NNvwHHQaem6PaSJwW8DEgeHJM6E",
  "items": [
    {
      "kind": "youtube#video",
      "etag": "xSZ27rZI1ZaTQEccNQETeTsnsog",
      "id": "3m5qxZm_JqM",
      "snippet": {
        "publishedAt": "2010-06-24T03:55:03Z",
        "channelId": "UCPyb1dDiGoZ07j_DKzam4sQ",
        "title": "Clarke and Dawe - The Front Fell Off",
        "description": "http://www.mrjohnclarke.com \r\n\r\n\"Bob Collins, Australian Senator\" Air date: 26/07/1991\r\n\r\nCan be purchased on \"Clarke & Dawe -The Full Catastrophe DVD Boxed Set\" Personally signed at MrJohnClarke.com",
        "thumbnails": {
          "default": {
            "url": "https://i.ytimg.com/vi/3m5qxZm_JqM/default.jpg",
            "width": 120,
            "height": 90
          },
          "medium": {
            "url": "https://i.ytimg.com/vi/3m5qxZm_JqM/mqdefault.jpg",
            "width": 320,
            "height": 180
          },
          "high": {
            "url": "https://i.ytimg.com/vi/3m5qxZm_JqM/hqdefault.jpg",
            "width": 480,
            "height": 360
          }
        },
        "channelTitle": "ClarkeAndDawe",
        "tags": [
          "the front fell off",
          "oil spill",
          "clarke & dawe",
          "clarke and dawe",
          "john clarke",
          "bryan dawe",
          "john clark",
          "clarke and dawes",
          "snopes",
          "brian dawe",
          "comedy",
          "australian"
        ],
        "categoryId": "25",
        "liveBroadcastContent": "none",
        "localized": {
          "title": "Clarke and Dawe - The Front Fell Off",
          "description": "http://www.mrjohnclarke.com \r\n\r\n\"Bob Collins, Australian Senator\" Air date: 26/07/1991\r\n\r\nCan be purchased on \"Clarke & Dawe -The Full Catastrophe DVD Boxed Set\" Personally signed at MrJohnClarke.com"
        }
      },
      "contentDetails": {
        "duration": "PT2M9S",
        "dimension": "2d",
        "definition": "sd",
        "caption": "true",
        "licensedContent": true,
        "contentRating": {},
        "projection": "rectangular"
      }
    }
  ],
  "pageInfo": {
    "totalResults": 1,
    "resultsPerPage": 1
  }
}
