{
  "kind": "youtube#videoListResponse",
  "etag": "PQHHuyvIHY4LTjQ9TSsBAeRpuRs",
  "items": [
    {
      "kind": "youtube#video",
      "etag": "eaZ2No_tXo5XRAsCMo02XJNjKq0",
      "id": "qs9VR6oF_74",
      "snippet": {
        "publishedAt": "2023-03-05T04:41:22Z",
        "channelId": "UCCWWrNJULTk4DPkMzlaaAPQ",
        "title": "Who Remembers “Numa Numa”?",
        "description": "Who remembers this video by @dorkdaily? I remember my friend showing me this when I would sleep over. Great content! This video is not my video. It was posted by Dork Daily. The original creator is @GaryBrolsma. \n\nOriginal Numa Numa Video: https://youtu.be/KmtzQCSh6xk\n\n\nSubscribe to the Original by Gary Brolsma:\n\nhttps://youtube.com/@GaryBrolsma\n\n\n\n\n\nSubscribe: @ShortsMaGeeTV \n\nCheck out my second channel: @SMTVStudios \n\nJoin Our Discord: https://www.discord.gg/bvf6Sk9Z\n\nFollow us on Facebook: https://www.facebook.com/shortsmagee\n\nSupport The Channel: https://www.buymeacoffee.com/shortsmagee\n\nNOW ON RUMBLE: https://rumble.com/user/ShortsMaGeeTV",
        "thumbnails": {
          "default": {
            "url": "https://i.ytimg.com/vi/qs9VR6oF_74/default.jpg",
            "width": 120,
            "height": 90
          },
          "medium": {
            "url": "https://i.ytimg.com/vi/qs9VR6oF_74/mqdefault.jpg",
            "width": 320,
            "height": 180
          },
          "high": {
            "url": "https://i.ytimg.com/vi/qs9VR6oF_74/hqdefault.jpg",
            "width": 480,
            "height": 360
          },
          "standard": {
            "url": "https://i.ytimg.com/vi/qs9VR6oF_74/sddefault.jpg",
            "width": 640,
            "height": 480
          }
        },
        "channelTitle": "Shorts MaGee TV",
        "categoryId": "25",
        "liveBroadcastContent": "none",
        "defaultLanguage": "en",
        "localized": {
          "title": "Who Remembers “Numa Numa”?",
          "description": "Who remembers this video by @dorkdaily? I remember my friend showing me this when I would sleep over. Great content! This video is not my video. It was posted by Dork Daily. The original creator is @GaryBrolsma. \n\nOriginal Numa Numa Video: https://youtu.be/KmtzQCSh6xk\n\n\nSubscribe to the Original by Gary Brolsma:\n\nhttps://youtube.com/@GaryBrolsma\n\n\n\n\n\nSubscribe: @ShortsMaGeeTV \n\nCheck out my second channel: @SMTVStudios \n\nJoin Our Discord: https://www.discord.gg/bvf6Sk9Z\n\nFollow us on Facebook: https://www.facebook.com/shortsmagee\n\nSupport The Channel: https://www.buymeacoffee.com/shortsmagee\n\nNOW ON RUMBLE: https://rumble.com/user/ShortsMaGeeTV"
        },
        "defaultAudioLanguage": "en"
      },
      "contentDetails": {
        "duration": "PT1M18S",
        "dimension": "2d",
        "definition": "sd",
        "caption": "false",
        "licensedContent": false,
        "contentRating": {},
        "projection": "rectangular"
      }
    }
  ],
  "pageInfo": {
    "totalResults": 1,
    "resultsPerPage": 1
  }
}